cpybuild/__init__.py
cpybuild/cli.py
cpybuild/core.py
cpybuild/tasks/__init__.py
cpybuild/tasks/build.py
cpybuild/tasks/clean.py
cpybuild/tasks/init.py
cpybuild/tasks/test.py
cpybuild-0.1.4.dist-info/licenses/LICENSE
cpybuild-0.1.4.dist-info/METADATA
cpybuild-0.1.4.dist-info/WHEEL
cpybuild-0.1.4.dist-info/entry_points.txt
cpybuild-0.1.4.dist-info/top_level.txt
cpybuild-0.1.4.dist-info/RECORD
