Metadata-Version: 2.4
Name: cpybuild
Version: 0.1.4
Summary: A Python build tool that transpiles Python code to C using Cython.
Author: jayendra1107
License: MIT License
Requires-Python: >=3.7
License-File: LICENSE
Requires-Dist: pyyaml
Requires-Dist: cython
Requires-Dist: setuptools
Requires-Dist: wheel
Dynamic: license-file
Dynamic: requires-python
